Workbook

Sheet Data
A1: Month | B1: Sales | C1: Profit | D1: Orders | F1: Category | G1: Sales | H1: Profit | J1: Segment | K1: Sales
A2: 2015-01 | B2: 14237 | C2: 2450 | D2: 32 | F2: Furniture | G2: 742000 | H2: 18451 | J2: Consumer | K2: 1161401
A3: 2015-02 | B3: 4520 | C3: 862 | D3: 28 | F3: Office Supplies | G3: 719047 | H3: 122491 | J3: Corporate | K3: 706146
A4: 2015-03 | B4: 55691 | C4: 499 | D4: 71 | F4: Technology | G4: 836154 | H4: 145455 | J4: Home Office | K4: 429653
A5: 2015-04 | B5: 28295 | C5: 3489 | D5: 66
A6: 2015-05 | B6: 23648 | C6: 2739 | D6: 69
A7: 2015-06 | B7: 34595 | C7: 4977 | D7: 66
A8: 2015-07 | B8: 33946 | C8: -841 | D8: 65 | F8: Region | G8: Sales | H8: Profit | I8: Margin
A9: 2015-08 | B9: 27909 | C9: 5318 | D9: 72 | F9: Central | G9: 501240 | H9: 39706 | I9: =H9/G9 -> 0.079215545
A10: 2015-09 | B10: 81777 | C10: 8328 | D10: 130 | F10: East | G10: 678781 | H10: 91523 | I10: =H10/G10 -> 0.13483436
A11: 2015-10 | B11: 31453 | C11: 3448 | D11: 78 | F11: South | G11: 391722 | H11: 46749 | I11: =H11/G11 -> 0.11934229
A12: 2015-11 | B12: 78629 | C12: 9292 | D12: 151 | F12: West | G12: 725458 | H12: 108418 | I12: =H12/G12 -> 0.14944766
A13: 2015-12 | B13: 69546 | C13: 8984 | D13: 141
A14: 2016-01 | B14: 18174 | C14: -3281 | D14: 29
A15: 2016-02 | B15: 11951 | C15: 2814 | D15: 36
A16: 2016-03 | B16: 38726 | C16: 9732 | D16: 79
A17: 2016-04 | B17: 34195 | C17: 4187 | D17: 72
A18: 2016-05 | B18: 30132 | C18: 4668 | D18: 74
A19: 2016-06 | B19: 24797 | C19: 3336 | D19: 68
A20: 2016-07 | B20: 28765 | C20: 3289 | D20: 66
A21: 2016-08 | B21: 36898 | C21: 5356 | D21: 68
A22: 2016-09 | B22: 64596 | C22: 8209 | D22: 140
A23: 2016-10 | B23: 31405 | C23: 2817 | D23: 87
A24: 2016-11 | B24: 75973 | C24: 12475 | D24: 158
... A49: 2018-12 | B49: 83829 | C49: 8483 | D49: 224

Sheet Dashboard
B2: SUPERSTORE SALES KPI DASHBOARD
B3: Source: Superstore retail dataset, 2015-2018 | All KPIs computed with live Excel formulas from the Data sheet
B5: Total Revenue | D5: Total Profit | F5: Profit Margin | H5: Total Orders | J5: Avg Order Value | L5: Best Month Rev.
B6: =SUM(Data!B2:B49) -> 2297199 | D6: =SUM(Data!C2:C49) -> 286398 | F6: =SUM(Data!C2:C49)/SUM(Data!B2:B49) -> 0.1246727 | H6: =SUM(Data!D2:D49) -> 5009 | J6: =SUM(Data!B2:B49)/SUM(Data!D2:D49) -> 458.61429 | L6: =MAX(Data!B2:B49) -> 118448

Sheet Top Products
A1: Category | B1: Sub-Category | C1: Sales | D1: Profit | E1: Qty | F1: Margin
A2: Technology | B2: Phones | C2: 330007 | D2: 44516 | E2: 3289 | F2: =D2/C2 -> 0.13489411
A3: Furniture | B3: Chairs | C3: 328449 | D3: 26590 | E3: 2356 | F3: =D3/C3 -> 0.080956252
A4: Office Supplies | B4: Storage | C4: 223844 | D4: 21279 | E4: 3158 | F4: =D4/C4 -> 0.095061739
A5: Furniture | B5: Tables | C5: 206966 | D5: -17725 | E5: 1241 | F5: =D5/C5 -> -0.085642086
A6: Office Supplies | B6: Binders | C6: 203413 | D6: 30222 | E6: 5974 | F6: =D6/C6 -> 0.14857457
A7: Technology | B7: Machines | C7: 189239 | D7: 3385 | E7: 440 | F7: =D7/C7 -> 0.017887433
A8: Technology | B8: Accessories | C8: 167380 | D8: 41937 | E8: 2976 | F8: =D8/C8 -> 0.25054965
A9: Technology | B9: Copiers | C9: 149528 | D9: 55618 | E9: 234 | F9: =D9/C9 -> 0.37195709
A10: Furniture | B10: Bookcases | C10: 114880 | D10: -3473 | E10: 868 | F10: =D10/C10 -> -0.030231546
A11: Office Supplies | B11: Appliances | C11: 107532 | D11: 18138 | E11: 1729 | F11: =D11/C11 -> 0.16867537
A12: Furniture | B12: Furnishings | C12: 91705 | D12: 13059 | E12: 3563 | F12: =D12/C12 -> 0.14240227
A13: Office Supplies | B13: Paper | C13: 78479 | D13: 34054 | E13: 5178 | F13: =D13/C13 -> 0.433925
... A18: Office Supplies | B18: Fasteners | C18: 3024 | D18: 950 | E18: 914 | F18: =D18/C18 -> 0.31415344
